setup.py
wc14/__init__.py
wc14/cli.py
wc14/current.py
wc14/summary.py
wc14/today.py
wc14.egg-info/PKG-INFO
wc14.egg-info/SOURCES.txt
wc14.egg-info/dependency_links.txt
wc14.egg-info/entry_points.txt
wc14.egg-info/requires.txt
wc14.egg-info/top_level.txt