Metadata-Version: 1.1
Name: wc14
Version: 0.2
Summary: Command line tool to keep you updated about Football world cup 2014.
Home-page: https://github.com/rajalokan/wc14
Author: Alok Kumar
Author-email: rajalokan@gmail.com
License: UNKNOWN
Download-URL: https://github.com/rajalokan/wc14/archive/0.1.tar.gz
Platform: UNKNOWN
